{
  "result_id": "fb2c371f-44e0-4f04-a7d5-e618ba32eb3f",
  "audio_filename": "Sample_Call.mp3",
  "analyzed_at": "2026-02-13T05:40:03.106617Z",
  "transcript": {
    "full_text": "Hello. Hello, Tim. Take the call. My name is Jesus with Clean and Sky Energy on our Reconnaissance Line. May I speak with Janini Correa? Yes, please. Hi, my name is Jesus. I work for ICL. I'm calling on behalf of Clean and Sky Energy. I'll ask in the letter supplier, Clean and Sky Energy is not affiliated with the local electricity utility or any city or town energy program. The line is recorded for quality purposes. Me and Janini, the reason of calling is because you may be eligible for the price to take it, or enable the electricity plan with their skin and your utility habits. Open and Sky Energy plan is lacking a fixed rate for the length of your contract. So no matter how high energy price will go up, your price for it is going to be not being crude during your challenge. Plastic will be raised up to $100 in this Agif course when you're all in Semisina. I just need to confirm that you qualify. Are you the counterholder or person authorized to make decision and account? Yes. Okay, do you receive any government assistance for your Anna's bill? No. Okay, are you raising the enrollment in Clean and Sky Energy? No. Okay, in any room time with the payments on your utility bill? No. Okay, perfect. I need to answer the bill, qualify. Now you can roll in these menu price for decision plan. I need to regret a copy of your electric bill. And let me know once you have it. Okay. Okay. How does the name of the bill appear? Even if it appears. Even if it appears. I need to put it in my name. Perfect. Perfect. And what is the service address? It appears in the bill. Even if it appears. It appears in the bill. Okay. If you have five, five, go drive. Welcome. And may also go one. Okay, in what's the seat code? O301. Okay, perfect. Perfect. Give me a moment. Is the bill that answered the same as the service address? Yes. Perfect. To provide it with the correct rate, what is the name of the utility company? No. National. National. Perfect. The number. 156. 96. 06. 0. 0. 0. Perfect. And your four number is 508-345-904, correct? Yes. Okay, great. Do you have three? For quality assurance purposes, when is your birthday? Just more than day. April 15. Perfect. Okay, great. Do you have any other electric bill for this or any other location? No. Okay. May I have your email address, ma'am? I need your call. Perfect. Perfect. Okay. Great. The echo requires 12,000, over 12,000, of 100, and you will receive your credit card. If you decide to cancel your price rotation plan after a recession period, there will be a small, early termination for the $0.75 per meter. The plan is to let you include $30 in this package card, how this works? At every seed money travels over the course of your free trade fund, you will receive a $25 in this package card, and you will see an up to 12 months. Your eligible for up to 12 months in the year to get the card, remain assuming you are in the app tick in a ghost penny. You will receive a notif for us between 30 and 45 days before the end of your account. The notice you will inform that your tenant's is east about to ask for you, anybody to call us to learn about the new red option available. If you do nothing, you read with automatically which two months to months, variable red will not cancelation of it. Perfect. Perfect. Now the last step is the verification process. It is a requirement about this stage, just to make sure that we have the correct information along with your request, I'm going to connect you with a 23rd party party. In the I'm going to reconfirm your name, the name of your utility company, the service address, account number, and the rate. They will assume that clean sky energy is not affiliated with utility company, in that utility company will still be the responsible for the related portion of your bill, reach the middle, build your in-hand low, any service calls and emergency. They will assume that you are going to receive a well-compact case in the next three to five business days, and nationally agreed with a sensation of a confirmation leader. Once you receive the welcome package, if you have any additional question, you can call call-comers, if you have a piece of papers that I can give you, or call-comers service numbers, is 888-355-6205. Now, during the verification process, they are not allowed to answer any question, therefore do you have any additional question? No, no, no. Okay, great. During the verification, if you have any question or you don't give a clear gesture, now the verification will be to be reserved. Okay, perfect. Let me leave the line. The first two questions are for me. Hope for one moment. If you didn't say it with me on the line, do not hint. Okay? Okay, perfect. Thank you. Thank you. Thank you. Hello, this is Sam with a TPV-36BM, and in the band-end third party, we are fire. Today, I will be confirming and recording your position. To voluntarily select the INSKY energy, as your electricity supplier, each question must be answered with a clear reaction or response, and last otherwise requested. The understanding purpose of this call in fact is being recorded. I'm sorry, can you hear your voice? Can you please repeat your response? Do you ask me a question? I'll answer your question. Yes, go now. Let me repeat. The understand, the purpose of this call in fact is being recorded. Yes. Please confirm today's date is April 9th, 2025, and the time is 11.45 AM, Eastern Standard Time. Please estate the customer name as it appears on the National Grid Bill. Janini Kurea. Please estate your first and last name. Janini, last name Kurea. Please estate your phone number. 5-0-8-345-6904. Thank you. Are you the utility bill account holder for person authorized to switch energy suppliers? Yes. I have your month and the birth as April 15th, is that your act? Yes. Is a 305 Pine Grove Drive, Brockton, MA-02300 on your correct service address? Yes. I show your billing address to be the same as your service address. Is this your act? That's correct, yes. I show the account number on your electric bill as 756-960-602-1 is that your act? Yes. The understand that you are enrolling in a fixed rate electricity plan, which is a 100% renewable product at a price of 20.99 cents per kilowatt hour for an initial term of 12 months? Yes. The understand that if you decide to cancel your electricity supply service before the end of the term, you may be charged in early termination fee and the amount of $75. Yes. Begin sent your allowing King Sky energy to you obtain your historical usage information from your utility company in order to process your enrollment request. Yes. The understand that the rubber sun that I've been spoke with earlier rubber suns, King Sky and that, King Sky is not an affiliate of national grid, what is an approved supplier in the energy choice program, these answer, critically or yes or no? Yes. I'm sorry your line is cutting in and out, can you please repeat it? Can you please say it again, please? Okay, let me repeat the question. Do you understand that the rubber sun that I've been with who you spoke with earlier rubber suns, Queen Sky and that, Queen Sky is not an affiliate of national grid, but is it approved supplier on the Viatters each voice program, please answer, critically or yes or no? Yes. Upon successful completion of this verification, Queen Sky energy will send you a welcome package in changing the terms of service for your review. By law, you have until midnight of the ferrid calendar day following receipt of the welcome packet to stop the enrollment process. And if you select that a plan that includes an early termination fee, you may be required to be a penalty after the rescission for your ends. To your rescind, your enrollment simply call either your utility company or Queen Sky energy at 888-3556-055. Do you understand? Yes. Lastly, your service with Queen Sky energy will begin with the next available meet your rebate or according to your utilities scheduled timeframe for initiating service. If you decide to cancel your service or if you have any questions about your service, you may call Queen Sky energy at 888-3556-055. Do you understand? Yes. Thank you for your responses and your verification is now complete. Your verification code is T-Lec Thomas 0701260. Thank you for using TBB360 and you have a great day. Goodbye for now.",
    "segment_count": 191
  },
  "overall_sentiment": "neutral",
  "overall_sentiment_score": 0.645653247833252,
  "overall_sentiment_scores": {
    "neutral": 0.645653247833252,
    "positive": 0.3456174433231354,
    "negative": 0.008729333057999611
  },
  "overall_tone": "Apologetic",
  "insights": [
    "Overall sentiment: neutral; tone perceived as Apologetic.",
    "Tone varied across the call; mid-call or closing tone may need attention."
  ],
  "segment_breakdown": [
    {
      "start": 0.0,
      "end": 2.0,
      "text": "Hello.",
      "sentiment": "positive",
      "sentiment_score": 0.5524577498435974,
      "tone": "Neutral",
      "scores": {
        "positive": 0.5524577498435974,
        "neutral": 0.4252780079841614,
        "negative": 0.022264264523983
      }
    },
    {
      "start": 2.0,
      "end": 5.0,
      "text": "Hello, Tim.",
      "sentiment": "neutral",
      "sentiment_score": 0.5444180369377136,
      "tone": "Neutral",
      "scores": {
        "neutral": 0.5444180369377136,
        "positive": 0.44472944736480713,
        "negative": 0.010852537117898464
      }
    },
    {
      "start": 5.0,
      "end": 7.0,
      "text": "Take the call.",
      "sentiment": "neutral",
      "sentiment_score": 0.7836224436759949,
      "tone": "Neutral",
      "scores": {
        "neutral": 0.7836224436759949,
        "positive": 0.1256721019744873,
        "negative": 0.09070539474487305
      }
    },
    {
      "start": 7.0,
      "end": 11.0,
      "text": "My name is Jesus with Clean and Sky Energy on our Reconnaissance Line.",
      "sentiment": "neutral",
      "sentiment_score": 0.6811535954475403,
      "tone": "Neutral",
      "scores": {
        "neutral": 0.6811535954475403,
        "positive": 0.3127971589565277,
        "negative": 0.006049200426787138
      }
    },
    {
      "start": 11.0,
      "end": 14.0,
      "text": "May I speak with Janini Correa?",
      "sentiment": "neutral",
      "sentiment_score": 0.9407680034637451,
      "tone": "Neutral",
      "scores": {
        "neutral": 0.9407680034637451,
        "positive": 0.0463360920548439,
        "negative": 0.01289596501737833
      }
    },
    {
      "start": 14.0,
      "end": 16.0,
      "text": "Yes, please.",
      "sentiment": "positive",
      "sentiment_score": 0.5949231386184692,
      "tone": "Professional",
      "scores": {
        "positive": 0.5949231386184692,
        "neutral": 0.3806614279747009,
        "negative": 0.024415455758571625
      }
    },
    {
      "start": 16.0,
      "end": 18.0,
      "text": "Hi, my name is Jesus.",
      "sentiment": "positive",
      "sentiment_score": 0.5349657535552979,
      "tone": "Neutral",
      "scores": {
        "positive": 0.5349657535552979,
        "neutral": 0.4576275944709778,
        "negative": 0.0074066342785954475
      }
    },
    {
      "start": 18.0,
      "end": 19.0,
      "text": "I work for ICL.",
      "sentiment": "neutral",
      "sentiment_score": 0.883084237575531,
      "tone": "Neutral",
      "scores": {
        "neutral": 0.883084237575531,
        "positive": 0.09381541609764099,
        "negative": 0.02310028485953808
      }
    },
    {
      "start": 19.0,
      "end": 22.0,
      "text": "I'm calling on behalf of Clean and Sky Energy.",
      "sentiment": "neutral",
      "sentiment_score": 0.8879741430282593,
      "tone": "Neutral",
      "scores": {
        "neutral": 0.8879741430282593,
        "positive": 0.09397511929273605,
        "negative": 0.01805081032216549
      }
    },
    {
      "start": 22.0,
      "end": 26.0,
      "text": "I'll ask in the letter supplier, Clean and Sky Energy is not affiliated with the local",
      "sentiment": "neutral",
      "sentiment_score": 0.8209055662155151,
      "tone": "Neutral",
      "scores": {
        "neutral": 0.8209055662155151,
        "negative": 0.1376359760761261,
        "positive": 0.04145850986242294
      }
    },
    {
      "start": 26.0,
      "end": 29.0,
      "text": "electricity utility or any city or town energy program.",
      "sentiment": "neutral",
      "sentiment_score": 0.9250180721282959,
      "tone": "Neutral",
      "scores": {
        "neutral": 0.9250180721282959,
        "negative": 0.03935730457305908,
        "positive": 0.03562456741929054
      }
    },
    {
      "start": 29.0,
      "end": 32.0,
      "text": "The line is recorded for quality purposes.",
      "sentiment": "neutral",
      "sentiment_score": 0.7990164160728455,
      "tone": "Neutral",
      "scores": {
        "neutral": 0.7990164160728455,
        "positive": 0.17480599880218506,
        "negative": 0.02617761492729187
      }
    },
    {
      "start": 32.0,
      "end": 36.0,
      "text": "Me and Janini, the reason of calling is because you may be eligible for the price",
      "sentiment": "neutral",
      "sentiment_score": 0.7134047150611877,
      "tone": "Neutral",
      "scores": {
        "neutral": 0.7134047150611877,
        "positive": 0.2747592628002167,
        "negative": 0.011836051009595394
      }
    },
    {
      "start": 36.0,
      "end": 40.0,
      "text": "to take it, or enable the electricity plan with their skin and your utility habits.",
      "sentiment": "neutral",
      "sentiment_score": 0.8754956722259521,
      "tone": "Neutral",
      "scores": {
        "neutral": 0.8754956722259521,
        "negative": 0.08981258422136307,
        "positive": 0.03469178453087807
      }
    },
    {
      "start": 40.0,
      "end": 44.0,
      "text": "Open and Sky Energy plan is lacking a fixed rate for the length of your contract.",
      "sentiment": "neutral",
      "sentiment_score": 0.5179369449615479,
      "tone": "Neutral",
      "scores": {
        "neutral": 0.5179369449615479,
        "negative": 0.4560437500476837,
        "positive": 0.026019318029284477
      }
    },
    {
      "start": 44.0,
      "end": 48.0,
      "text": "So no matter how high energy price will go up, your price for it is going to be not",
      "sentiment": "neutral",
      "sentiment_score": 0.5229686498641968,
      "tone": "Neutral",
      "scores": {
        "neutral": 0.5229686498641968,
        "negative": 0.43341249227523804,
        "positive": 0.04361886903643608
      }
    },
    {
      "start": 48.0,
      "end": 50.0,
      "text": "being crude during your challenge.",
      "sentiment": "neutral",
      "sentiment_score": 0.5981346964836121,
      "tone": "Neutral",
      "scores": {
        "neutral": 0.5981346964836121,
        "negative": 0.36354121565818787,
        "positive": 0.038324024528265
      }
    },
    {
      "start": 50.0,
      "end": 54.0,
      "text": "Plastic will be raised up to $100 in this Agif course when you're all in Semisina.",
      "sentiment": "neutral",
      "sentiment_score": 0.8599419593811035,
      "tone": "Neutral",
      "scores": {
        "neutral": 0.8599419593811035,
        "positive": 0.09509037435054779,
        "negative": 0.04496769234538078
      }
    },
    {
      "start": 54.0,
      "end": 56.0,
      "text": "I just need to confirm that you qualify.",
      "sentiment": "neutral",
      "sentiment_score": 0.6647908091545105,
      "tone": "Rushed",
      "scores": {
        "neutral": 0.6647908091545105,
        "positive": 0.3166991174221039,
        "negative": 0.018510082736611366
      }
    },
    {
      "start": 56.0,
      "end": 61.0,
      "text": "Are you the counterholder or person authorized to make decision and account?",
      "sentiment": "neutral",
      "sentiment_score": 0.8900132179260254,
      "tone": "Neutral",
      "scores": {
        "neutral": 0.8900132179260254,
        "negative": 0.06947562843561172,
        "positive": 0.040511153638362885
      }
    },
    {
      "start": 61.0,
      "end": 62.0,
      "text": "Yes.",
      "sentiment": "neutral",
      "sentiment_score": 0.5811466574668884,
      "tone": "Neutral",
      "scores": {
        "neutral": 0.5811466574668884,
        "positive": 0.3446405827999115,
        "negative": 0.07421278953552246
      }
    },
    {
      "start": 62.0,
      "end": 66.0,
      "text": "Okay, do you receive any government assistance for your Anna's bill?",
      "sentiment": "neutral",
      "sentiment_score": 0.9085463285446167,
      "tone": "Neutral",
      "scores": {
        "neutral": 0.9085463285446167,
        "negative": 0.06417401134967804,
        "positive": 0.0272796880453825
      }
    },
    {
      "start": 66.0,
      "end": 68.0,
      "text": "No.",
      "sentiment": "neutral",
      "sentiment_score": 0.5609908103942871,
      "tone": "Neutral",
      "scores": {
        "neutral": 0.5609908103942871,
        "positive": 0.28052860498428345,
        "negative": 0.15848061442375183
      }
    },
    {
      "start": 68.0,
      "end": 72.0,
      "text": "Okay, are you raising the enrollment in Clean and Sky Energy?",
      "sentiment": "neutral",
      "sentiment_score": 0.9294934868812561,
      "tone": "Neutral",
      "scores": {
        "neutral": 0.9294934868812561,
        "positive": 0.05928380787372589,
        "negative": 0.011222656816244125
      }
    },
    {
      "start": 72.0,
      "end": 74.0,
      "text": "No.",
      "sentiment": "neutral",
      "sentiment_score": 0.5609908103942871,
      "tone": "Neutral",
      "scores": {
        "neutral": 0.5609908103942871,
        "positive": 0.28052860498428345,
        "negative": 0.15848061442375183
      }
    },
    {
      "start": 74.0,
      "end": 78.0,
      "text": "Okay, in any room time with the payments on your utility bill?",
      "sentiment": "neutral",
      "sentiment_score": 0.9365628361701965,
      "tone": "Neutral",
      "scores": {
        "neutral": 0.9365628361701965,
        "positive": 0.03552961349487305,
        "negative": 0.027907533571124077
      }
    },
    {
      "start": 78.0,
      "end": 80.0,
      "text": "No.",
      "sentiment": "neutral",
      "sentiment_score": 0.5609908103942871,
      "tone": "Neutral",
      "scores": {
        "neutral": 0.5609908103942871,
        "positive": 0.28052860498428345,
        "negative": 0.15848061442375183
      }
    },
    {
      "start": 80.0,
      "end": 81.0,
      "text": "Okay, perfect.",
      "sentiment": "positive",
      "sentiment_score": 0.9282195568084717,
      "tone": "Neutral",
      "scores": {
        "positive": 0.9282195568084717,
        "neutral": 0.06015513837337494,
        "negative": 0.011625300161540508
      }
    },
    {
      "start": 81.0,
      "end": 83.0,
      "text": "I need to answer the bill, qualify.",
      "sentiment": "neutral",
      "sentiment_score": 0.8506675362586975,
      "tone": "Neutral",
      "scores": {
        "neutral": 0.8506675362586975,
        "negative": 0.09042329341173172,
        "positive": 0.05890912935137749
      }
    },
    {
      "start": 83.0,
      "end": 85.0,
      "text": "Now you can roll in these menu price for decision plan.",
      "sentiment": "neutral",
      "sentiment_score": 0.9009448289871216,
      "tone": "Neutral",
      "scores": {
        "neutral": 0.9009448289871216,
        "positive": 0.07650869339704514,
        "negative": 0.022546518594026566
      }
    },
    {
      "start": 85.0,
      "end": 87.0,
      "text": "I need to regret a copy of your electric bill.",
      "sentiment": "negative",
      "sentiment_score": 0.8316588997840881,
      "tone": "Apologetic",
      "scores": {
        "negative": 0.8316588997840881,
        "neutral": 0.15622781217098236,
        "positive": 0.012113334611058235
      }
    },
    {
      "start": 87.0,
      "end": 89.0,
      "text": "And let me know once you have it.",
      "sentiment": "neutral",
      "sentiment_score": 0.7750624418258667,
      "tone": "Neutral",
      "scores": {
        "neutral": 0.7750624418258667,
        "positive": 0.20849575102329254,
        "negative": 0.016441818326711655
      }
    },
    {
      "start": 89.0,
      "end": 91.0,
      "text": "Okay.",
      "sentiment": "neutral",
      "sentiment_score": 0.5692523121833801,
      "tone": "Neutral",
      "scores": {
        "neutral": 0.5692523121833801,
        "positive": 0.3558010458946228,
        "negative": 0.07494664192199707
      }
    },
    {
      "start": 91.0,
      "end": 92.0,
      "text": "Okay.",
      "sentiment": "neutral",
      "sentiment_score": 0.5692523121833801,
      "tone": "Neutral",
      "scores": {
        "neutral": 0.5692523121833801,
        "positive": 0.3558010458946228,
        "negative": 0.07494664192199707
      }
    },
    {
      "start": 92.0,
      "end": 94.0,
      "text": "How does the name of the bill appear?",
      "sentiment": "neutral",
      "sentiment_score": 0.9266848564147949,
      "tone": "Neutral",
      "scores": {
        "neutral": 0.9266848564147949,
        "negative": 0.04802697151899338,
        "positive": 0.025288205593824387
      }
    },
    {
      "start": 94.0,
      "end": 96.0,
      "text": "Even if it appears.",
      "sentiment": "neutral",
      "sentiment_score": 0.7032424211502075,
      "tone": "Neutral",
      "scores": {
        "neutral": 0.7032424211502075,
        "negative": 0.183015838265419,
        "positive": 0.11374174803495407
      }
    },
    {
      "start": 96.0,
      "end": 99.0,
      "text": "Even if it appears.",
      "sentiment": "neutral",
      "sentiment_score": 0.7032424211502075,
      "tone": "Neutral",
      "scores": {
        "neutral": 0.7032424211502075,
        "negative": 0.183015838265419,
        "positive": 0.11374174803495407
      }
    },
    {
      "start": 99.0,
      "end": 102.0,
      "text": "I need to put it in my name.",
      "sentiment": "neutral",
      "sentiment_score": 0.8688285946846008,
      "tone": "Neutral",
      "scores": {
        "neutral": 0.8688285946846008,
        "positive": 0.08211501687765121,
        "negative": 0.04905633628368378
      }
    },
    {
      "start": 102.0,
      "end": 103.0,
      "text": "Perfect.",
      "sentiment": "positive",
      "sentiment_score": 0.90750652551651,
      "tone": "Neutral",
      "scores": {
        "positive": 0.90750652551651,
        "neutral": 0.07291112095117569,
        "negative": 0.019582388922572136
      }
    },
    {
      "start": 103.0,
      "end": 104.0,
      "text": "Perfect.",
      "sentiment": "positive",
      "sentiment_score": 0.90750652551651,
      "tone": "Neutral",
      "scores": {
        "positive": 0.90750652551651,
        "neutral": 0.07291112095117569,
        "negative": 0.019582388922572136
      }
    },
    {
      "start": 104.0,
      "end": 105.0,
      "text": "And what is the service address?",
      "sentiment": "neutral",
      "sentiment_score": 0.9078978300094604,
      "tone": "Neutral",
      "scores": {
        "neutral": 0.9078978300094604,
        "negative": 0.0593542717397213,
        "positive": 0.032747991383075714
      }
    },
    {
      "start": 105.0,
      "end": 106.0,
      "text": "It appears in the bill.",
      "sentiment": "neutral",
      "sentiment_score": 0.8877149224281311,
      "tone": "Neutral",
      "scores": {
        "neutral": 0.8877149224281311,
        "positive": 0.09324528276920319,
        "negative": 0.019039753824472427
      }
    },
    {
      "start": 106.0,
      "end": 108.0,
      "text": "Even if it appears.",
      "sentiment": "neutral",
      "sentiment_score": 0.7032424211502075,
      "tone": "Neutral",
      "scores": {
        "neutral": 0.7032424211502075,
        "negative": 0.183015838265419,
        "positive": 0.11374174803495407
      }
    },
    {
      "start": 108.0,
      "end": 110.0,
      "text": "It appears in the bill.",
      "sentiment": "neutral",
      "sentiment_score": 0.8877149224281311,
      "tone": "Neutral",
      "scores": {
        "neutral": 0.8877149224281311,
        "positive": 0.09324528276920319,
        "negative": 0.019039753824472427
      }
    },
    {
      "start": 110.0,
      "end": 111.0,
      "text": "Okay.",
      "sentiment": "neutral",
      "sentiment_score": 0.5692523121833801,
      "tone": "Neutral",
      "scores": {
        "neutral": 0.5692523121833801,
        "positive": 0.3558010458946228,
        "negative": 0.07494664192199707
      }
    },
    {
      "start": 111.0,
      "end": 113.0,
      "text": "If you have five, five, go drive.",
      "sentiment": "neutral",
      "sentiment_score": 0.7195911407470703,
      "tone": "Neutral",
      "scores": {
        "neutral": 0.7195911407470703,
        "positive": 0.24213555455207825,
        "negative": 0.03827325627207756
      }
    },
    {
      "start": 113.0,
      "end": 114.0,
      "text": "Welcome.",
      "sentiment": "positive",
      "sentiment_score": 0.7742796540260315,
      "tone": "Neutral",
      "scores": {
        "positive": 0.7742796540260315,
        "neutral": 0.2035432606935501,
        "negative": 0.022177016362547874
      }
    },
    {
      "start": 114.0,
      "end": 116.0,
      "text": "And may also go one.",
      "sentiment": "neutral",
      "sentiment_score": 0.7968025207519531,
      "tone": "Neutral",
      "scores": {
        "neutral": 0.7968025207519531,
        "positive": 0.1801130175590515,
        "negative": 0.023084422573447227
      }
    },
    {
      "start": 116.0,
      "end": 118.0,
      "text": "Okay, in what's the seat code?",
      "sentiment": "neutral",
      "sentiment_score": 0.9393707513809204,
      "tone": "Neutral",
      "scores": {
        "neutral": 0.9393707513809204,
        "positive": 0.037261802703142166,
        "negative": 0.02336742728948593
      }
    },
    {
      "start": 118.0,
      "end": 120.0,
      "text": "O301.",
      "sentiment": "neutral",
      "sentiment_score": 0.6972922086715698,
      "tone": "Neutral",
      "scores": {
        "neutral": 0.6972922086715698,
        "positive": 0.16984866559505463,
        "negative": 0.13285914063453674
      }
    },
    {
      "start": 120.0,
      "end": 121.0,
      "text": "Okay, perfect.",
      "sentiment": "positive",
      "sentiment_score": 0.9282195568084717,
      "tone": "Neutral",
      "scores": {
        "positive": 0.9282195568084717,
        "neutral": 0.06015513837337494,
        "negative": 0.011625300161540508
      }
    },
    {
      "start": 121.0,
      "end": 122.0,
      "text": "Perfect.",
      "sentiment": "positive",
      "sentiment_score": 0.90750652551651,
      "tone": "Neutral",
      "scores": {
        "positive": 0.90750652551651,
        "neutral": 0.07291112095117569,
        "negative": 0.019582388922572136
      }
    },
    {
      "start": 122.0,
      "end": 123.0,
      "text": "Give me a moment.",
      "sentiment": "neutral",
      "sentiment_score": 0.794593870639801,
      "tone": "Neutral",
      "scores": {
        "neutral": 0.794593870639801,
        "positive": 0.1267860233783722,
        "negative": 0.0786200538277626
      }
    },
    {
      "start": 123.0,
      "end": 126.0,
      "text": "Is the bill that answered the same as the service address?",
      "sentiment": "neutral",
      "sentiment_score": 0.9134622812271118,
      "tone": "Neutral",
      "scores": {
        "neutral": 0.9134622812271118,
        "negative": 0.06353874504566193,
        "positive": 0.022998999804258347
      }
    },
    {
      "start": 126.0,
      "end": 127.0,
      "text": "Yes.",
      "sentiment": "neutral",
      "sentiment_score": 0.5811466574668884,
      "tone": "Neutral",
      "scores": {
        "neutral": 0.5811466574668884,
        "positive": 0.3446405827999115,
        "negative": 0.07421278953552246
      }
    },
    {
      "start": 127.0,
      "end": 128.0,
      "text": "Perfect.",
      "sentiment": "positive",
      "sentiment_score": 0.90750652551651,
      "tone": "Neutral",
      "scores": {
        "positive": 0.90750652551651,
        "neutral": 0.07291112095117569,
        "negative": 0.019582388922572136
      }
    },
    {
      "start": 128.0,
      "end": 132.0,
      "text": "To provide it with the correct rate, what is the name of the utility company?",
      "sentiment": "neutral",
      "sentiment_score": 0.918890655040741,
      "tone": "Neutral",
      "scores": {
        "neutral": 0.918890655040741,
        "positive": 0.04353412240743637,
        "negative": 0.03757521137595177
      }
    },
    {
      "start": 132.0,
      "end": 133.0,
      "text": "No.",
      "sentiment": "neutral",
      "sentiment_score": 0.5609908103942871,
      "tone": "Neutral",
      "scores": {
        "neutral": 0.5609908103942871,
        "positive": 0.28052860498428345,
        "negative": 0.15848061442375183
      }
    },
    {
      "start": 133.0,
      "end": 134.0,
      "text": "National.",
      "sentiment": "neutral",
      "sentiment_score": 0.6650879383087158,
      "tone": "Neutral",
      "scores": {
        "neutral": 0.6650879383087158,
        "positive": 0.25522395968437195,
        "negative": 0.07968802750110626
      }
    },
    {
      "start": 134.0,
      "end": 135.0,
      "text": "National.",
      "sentiment": "neutral",
      "sentiment_score": 0.6650879383087158,
      "tone": "Neutral",
      "scores": {
        "neutral": 0.6650879383087158,
        "positive": 0.25522395968437195,
        "negative": 0.07968802750110626
      }
    },
    {
      "start": 135.0,
      "end": 136.0,
      "text": "Perfect.",
      "sentiment": "positive",
      "sentiment_score": 0.90750652551651,
      "tone": "Neutral",
      "scores": {
        "positive": 0.90750652551651,
        "neutral": 0.07291112095117569,
        "negative": 0.019582388922572136
      }
    },
    {
      "start": 136.0,
      "end": 138.0,
      "text": "The number.",
      "sentiment": "neutral",
      "sentiment_score": 0.811987578868866,
      "tone": "Neutral",
      "scores": {
        "neutral": 0.811987578868866,
        "negative": 0.09427115321159363,
        "positive": 0.09374129772186279
      }
    },
    {
      "start": 138.0,
      "end": 140.0,
      "text": "156.",
      "sentiment": "neutral",
      "sentiment_score": 0.7546960115432739,
      "tone": "Neutral",
      "scores": {
        "neutral": 0.7546960115432739,
        "positive": 0.20059716701507568,
        "negative": 0.0447067990899086
      }
    },
    {
      "start": 140.0,
      "end": 142.0,
      "text": "96.",
      "sentiment": "neutral",
      "sentiment_score": 0.6416504383087158,
      "tone": "Neutral",
      "scores": {
        "neutral": 0.6416504383087158,
        "positive": 0.2921958863735199,
        "negative": 0.06615369021892548
      }
    },
    {
      "start": 142.0,
      "end": 143.0,
      "text": "06.",
      "sentiment": "neutral",
      "sentiment_score": 0.7081238031387329,
      "tone": "Neutral",
      "scores": {
        "neutral": 0.7081238031387329,
        "positive": 0.2254507839679718,
        "negative": 0.06642542779445648
      }
    },
    {
      "start": 143.0,
      "end": 145.0,
      "text": "0.",
      "sentiment": "neutral",
      "sentiment_score": 0.7058559656143188,
      "tone": "Neutral",
      "scores": {
        "neutral": 0.7058559656143188,
        "positive": 0.21388959884643555,
        "negative": 0.08025451004505157
      }
    },
    {
      "start": 145.0,
      "end": 146.0,
      "text": "0.",
      "sentiment": "neutral",
      "sentiment_score": 0.7058559656143188,
      "tone": "Neutral",
      "scores": {
        "neutral": 0.7058559656143188,
        "positive": 0.21388959884643555,
        "negative": 0.08025451004505157
      }
    },
    {
      "start": 146.0,
      "end": 147.0,
      "text": "0.",
      "sentiment": "neutral",
      "sentiment_score": 0.7058559656143188,
      "tone": "Neutral",
      "scores": {
        "neutral": 0.7058559656143188,
        "positive": 0.21388959884643555,
        "negative": 0.08025451004505157
      }
    },
    {
      "start": 147.0,
      "end": 148.0,
      "text": "Perfect.",
      "sentiment": "positive",
      "sentiment_score": 0.90750652551651,
      "tone": "Neutral",
      "scores": {
        "positive": 0.90750652551651,
        "neutral": 0.07291112095117569,
        "negative": 0.019582388922572136
      }
    },
    {
      "start": 148.0,
      "end": 155.0,
      "text": "And your four number is 508-345-904, correct?",
      "sentiment": "neutral",
      "sentiment_score": 0.9070808291435242,
      "tone": "Neutral",
      "scores": {
        "neutral": 0.9070808291435242,
        "positive": 0.04863731935620308,
        "negative": 0.04428188130259514
      }
    },
    {
      "start": 155.0,
      "end": 156.0,
      "text": "Yes.",
      "sentiment": "neutral",
      "sentiment_score": 0.5811466574668884,
      "tone": "Neutral",
      "scores": {
        "neutral": 0.5811466574668884,
        "positive": 0.3446405827999115,
        "negative": 0.07421278953552246
      }
    },
    {
      "start": 156.0,
      "end": 157.0,
      "text": "Okay, great.",
      "sentiment": "positive",
      "sentiment_score": 0.9291729927062988,
      "tone": "Neutral",
      "scores": {
        "positive": 0.9291729927062988,
        "neutral": 0.06066695973277092,
        "negative": 0.01016008947044611
      }
    },
    {
      "start": 157.0,
      "end": 159.0,
      "text": "Do you have three?",
      "sentiment": "neutral",
      "sentiment_score": 0.9139445424079895,
      "tone": "Neutral",
      "scores": {
        "neutral": 0.9139445424079895,
        "positive": 0.07381990551948547,
        "negative": 0.012235604226589203
      }
    },
    {
      "start": 159.0,
      "end": 163.0,
      "text": "For quality assurance purposes, when is your birthday?",
      "sentiment": "neutral",
      "sentiment_score": 0.9260014295578003,
      "tone": "Neutral",
      "scores": {
        "neutral": 0.9260014295578003,
        "positive": 0.06301778554916382,
        "negative": 0.010980813764035702
      }
    },
    {
      "start": 163.0,
      "end": 165.0,
      "text": "Just more than day.",
      "sentiment": "neutral",
      "sentiment_score": 0.6571765542030334,
      "tone": "Neutral",
      "scores": {
        "neutral": 0.6571765542030334,
        "positive": 0.2168208211660385,
        "negative": 0.12600263953208923
      }
    },
    {
      "start": 166.0,
      "end": 168.0,
      "text": "April 15.",
      "sentiment": "neutral",
      "sentiment_score": 0.8809201717376709,
      "tone": "Neutral",
      "scores": {
        "neutral": 0.8809201717376709,
        "positive": 0.10182446986436844,
        "negative": 0.01725539192557335
      }
    },
    {
      "start": 168.0,
      "end": 169.0,
      "text": "Perfect.",
      "sentiment": "positive",
      "sentiment_score": 0.90750652551651,
      "tone": "Neutral",
      "scores": {
        "positive": 0.90750652551651,
        "neutral": 0.07291112095117569,
        "negative": 0.019582388922572136
      }
    },
    {
      "start": 169.0,
      "end": 170.0,
      "text": "Okay, great.",
      "sentiment": "positive",
      "sentiment_score": 0.9291729927062988,
      "tone": "Neutral",
      "scores": {
        "positive": 0.9291729927062988,
        "neutral": 0.06066695973277092,
        "negative": 0.01016008947044611
      }
    },
    {
      "start": 170.0,
      "end": 173.0,
      "text": "Do you have any other electric bill for this or any other location?",
      "sentiment": "neutral",
      "sentiment_score": 0.9444922208786011,
      "tone": "Neutral",
      "scores": {
        "neutral": 0.9444922208786011,
        "negative": 0.03669579327106476,
        "positive": 0.018811864778399467
      }
    },
    {
      "start": 173.0,
      "end": 174.0,
      "text": "No.",
      "sentiment": "neutral",
      "sentiment_score": 0.5609908103942871,
      "tone": "Neutral",
      "scores": {
        "neutral": 0.5609908103942871,
        "positive": 0.28052860498428345,
        "negative": 0.15848061442375183
      }
    },
    {
      "start": 174.0,
      "end": 175.0,
      "text": "Okay.",
      "sentiment": "neutral",
      "sentiment_score": 0.5692523121833801,
      "tone": "Neutral",
      "scores": {
        "neutral": 0.5692523121833801,
        "positive": 0.3558010458946228,
        "negative": 0.07494664192199707
      }
    },
    {
      "start": 175.0,
      "end": 180.0,
      "text": "May I have your email address, ma'am?",
      "sentiment": "neutral",
      "sentiment_score": 0.89546138048172,
      "tone": "Neutral",
      "scores": {
        "neutral": 0.89546138048172,
        "positive": 0.08648490905761719,
        "negative": 0.0180536936968565
      }
    },
    {
      "start": 180.0,
      "end": 184.0,
      "text": "I need your call.",
      "sentiment": "neutral",
      "sentiment_score": 0.7193757891654968,
      "tone": "Neutral",
      "scores": {
        "neutral": 0.7193757891654968,
        "positive": 0.2147516906261444,
        "negative": 0.06587247550487518
      }
    },
    {
      "start": 184.0,
      "end": 185.0,
      "text": "Perfect.",
      "sentiment": "positive",
      "sentiment_score": 0.90750652551651,
      "tone": "Neutral",
      "scores": {
        "positive": 0.90750652551651,
        "neutral": 0.07291112095117569,
        "negative": 0.019582388922572136
      }
    },
    {
      "start": 185.0,
      "end": 186.0,
      "text": "Perfect.",
      "sentiment": "positive",
      "sentiment_score": 0.90750652551651,
      "tone": "Neutral",
      "scores": {
        "positive": 0.90750652551651,
        "neutral": 0.07291112095117569,
        "negative": 0.019582388922572136
      }
    },
    {
      "start": 186.0,
      "end": 187.0,
      "text": "Okay.",
      "sentiment": "neutral",
      "sentiment_score": 0.5692523121833801,
      "tone": "Neutral",
      "scores": {
        "neutral": 0.5692523121833801,
        "positive": 0.3558010458946228,
        "negative": 0.07494664192199707
      }
    },
    {
      "start": 187.0,
      "end": 188.0,
      "text": "Great.",
      "sentiment": "positive",
      "sentiment_score": 0.8795905113220215,
      "tone": "Neutral",
      "scores": {
        "positive": 0.8795905113220215,
        "neutral": 0.10063043981790543,
        "negative": 0.019779076799750328
      }
    },
    {
      "start": 188.0,
      "end": 191.0,
      "text": "The echo requires 12,000, over 12,000, of 100,",
      "sentiment": "neutral",
      "sentiment_score": 0.8197963833808899,
      "tone": "Neutral",
      "scores": {
        "neutral": 0.8197963833808899,
        "positive": 0.1431044191122055,
        "negative": 0.037099242210388184
      }
    },
    {
      "start": 221.0,
      "end": 223.0,
      "text": "and you will receive your credit card.",
      "sentiment": "neutral",
      "sentiment_score": 0.7894211411476135,
      "tone": "Neutral",
      "scores": {
        "neutral": 0.7894211411476135,
        "positive": 0.19088301062583923,
        "negative": 0.019695837050676346
      }
    },
    {
      "start": 223.0,
      "end": 227.0,
      "text": "If you decide to cancel your price rotation plan after a recession period,",
      "sentiment": "neutral",
      "sentiment_score": 0.5763013362884521,
      "tone": "Neutral",
      "scores": {
        "neutral": 0.5763013362884521,
        "negative": 0.40424954891204834,
        "positive": 0.01944912225008011
      }
    },
    {
      "start": 227.0,
      "end": 231.0,
      "text": "there will be a small, early termination for the $0.75 per meter.",
      "sentiment": "neutral",
      "sentiment_score": 0.9227815270423889,
      "tone": "Neutral",
      "scores": {
        "neutral": 0.9227815270423889,
        "negative": 0.04228364676237106,
        "positive": 0.03493489697575569
      }
    },
    {
      "start": 231.0,
      "end": 235.0,
      "text": "The plan is to let you include $30 in this package card, how this works?",
      "sentiment": "neutral",
      "sentiment_score": 0.9062195420265198,
      "tone": "Neutral",
      "scores": {
        "neutral": 0.9062195420265198,
        "positive": 0.087134450674057,
        "negative": 0.006645986810326576
      }
    },
    {
      "start": 235.0,
      "end": 240.0,
      "text": "At every seed money travels over the course of your free trade fund,",
      "sentiment": "neutral",
      "sentiment_score": 0.8690575361251831,
      "tone": "Neutral",
      "scores": {
        "neutral": 0.8690575361251831,
        "positive": 0.07575071603059769,
        "negative": 0.05519186705350876
      }
    },
    {
      "start": 240.0,
      "end": 244.0,
      "text": "you will receive a $25 in this package card, and you will see an up to 12 months.",
      "sentiment": "neutral",
      "sentiment_score": 0.7426430583000183,
      "tone": "Neutral",
      "scores": {
        "neutral": 0.7426430583000183,
        "positive": 0.25138744711875916,
        "negative": 0.005969504360109568
      }
    },
    {
      "start": 244.0,
      "end": 248.0,
      "text": "Your eligible for up to 12 months in the year to get the card, remain assuming you are",
      "sentiment": "neutral",
      "sentiment_score": 0.8305507302284241,
      "tone": "Neutral",
      "scores": {
        "neutral": 0.8305507302284241,
        "positive": 0.15907160937786102,
        "negative": 0.010377696715295315
      }
    },
    {
      "start": 248.0,
      "end": 250.0,
      "text": "in the app tick in a ghost penny.",
      "sentiment": "neutral",
      "sentiment_score": 0.8345437049865723,
      "tone": "Neutral",
      "scores": {
        "neutral": 0.8345437049865723,
        "positive": 0.10302194952964783,
        "negative": 0.06243434548377991
      }
    },
    {
      "start": 250.0,
      "end": 254.0,
      "text": "You will receive a notif for us between 30 and 45 days before the end of your account.",
      "sentiment": "neutral",
      "sentiment_score": 0.9281600117683411,
      "tone": "Neutral",
      "scores": {
        "neutral": 0.9281600117683411,
        "positive": 0.06201593950390816,
        "negative": 0.009824085980653763
      }
    },
    {
      "start": 254.0,
      "end": 257.0,
      "text": "The notice you will inform that your tenant's is east about to ask for you,",
      "sentiment": "neutral",
      "sentiment_score": 0.896157443523407,
      "tone": "Neutral",
      "scores": {
        "neutral": 0.896157443523407,
        "negative": 0.06643287092447281,
        "positive": 0.03740977123379707
      }
    },
    {
      "start": 257.0,
      "end": 261.0,
      "text": "anybody to call us to learn about the new red option available.",
      "sentiment": "neutral",
      "sentiment_score": 0.9306944608688354,
      "tone": "Neutral",
      "scores": {
        "neutral": 0.9306944608688354,
        "positive": 0.0511789470911026,
        "negative": 0.0181265939027071
      }
    },
    {
      "start": 261.0,
      "end": 264.0,
      "text": "If you do nothing, you read with automatically which two months to months,",
      "sentiment": "neutral",
      "sentiment_score": 0.6559082865715027,
      "tone": "Neutral",
      "scores": {
        "neutral": 0.6559082865715027,
        "negative": 0.29033899307250977,
        "positive": 0.05375278368592262
      }
    },
    {
      "start": 264.0,
      "end": 266.0,
      "text": "variable red will not cancelation of it.",
      "sentiment": "neutral",
      "sentiment_score": 0.7890587449073792,
      "tone": "Neutral",
      "scores": {
        "neutral": 0.7890587449073792,
        "negative": 0.1538040190935135,
        "positive": 0.05713728442788124
      }
    },
    {
      "start": 266.0,
      "end": 267.0,
      "text": "Perfect.",
      "sentiment": "positive",
      "sentiment_score": 0.90750652551651,
      "tone": "Neutral",
      "scores": {
        "positive": 0.90750652551651,
        "neutral": 0.07291112095117569,
        "negative": 0.019582388922572136
      }
    },
    {
      "start": 267.0,
      "end": 268.0,
      "text": "Perfect.",
      "sentiment": "positive",
      "sentiment_score": 0.90750652551651,
      "tone": "Neutral",
      "scores": {
        "positive": 0.90750652551651,
        "neutral": 0.07291112095117569,
        "negative": 0.019582388922572136
      }
    },
    {
      "start": 268.0,
      "end": 270.0,
      "text": "Now the last step is the verification process.",
      "sentiment": "neutral",
      "sentiment_score": 0.8522621393203735,
      "tone": "Neutral",
      "scores": {
        "neutral": 0.8522621393203735,
        "positive": 0.12113280594348907,
        "negative": 0.026604998856782913
      }
    },
    {
      "start": 270.0,
      "end": 274.0,
      "text": "It is a requirement about this stage, just to make sure that we have the correct",
      "sentiment": "neutral",
      "sentiment_score": 0.8274597525596619,
      "tone": "Neutral",
      "scores": {
        "neutral": 0.8274597525596619,
        "positive": 0.13427512347698212,
        "negative": 0.038265179842710495
      }
    },
    {
      "start": 274.0,
      "end": 277.0,
      "text": "information along with your request, I'm going to connect you with a",
      "sentiment": "neutral",
      "sentiment_score": 0.8896942734718323,
      "tone": "Neutral",
      "scores": {
        "neutral": 0.8896942734718323,
        "positive": 0.08287655562162399,
        "negative": 0.02742914855480194
      }
    },
    {
      "start": 277.0,
      "end": 278.0,
      "text": "23rd party party.",
      "sentiment": "neutral",
      "sentiment_score": 0.8672614693641663,
      "tone": "Neutral",
      "scores": {
        "neutral": 0.8672614693641663,
        "negative": 0.07954805344343185,
        "positive": 0.053190458565950394
      }
    },
    {
      "start": 278.0,
      "end": 282.0,
      "text": "In the I'm going to reconfirm your name, the name of your utility company,",
      "sentiment": "neutral",
      "sentiment_score": 0.9047253727912903,
      "tone": "Neutral",
      "scores": {
        "neutral": 0.9047253727912903,
        "positive": 0.08003834635019302,
        "negative": 0.015236346051096916
      }
    },
    {
      "start": 282.0,
      "end": 285.0,
      "text": "the service address, account number, and the rate.",
      "sentiment": "neutral",
      "sentiment_score": 0.90987628698349,
      "tone": "Neutral",
      "scores": {
        "neutral": 0.90987628698349,
        "positive": 0.04895789548754692,
        "negative": 0.04116588085889816
      }
    },
    {
      "start": 285.0,
      "end": 288.0,
      "text": "They will assume that clean sky energy is not affiliated with utility company,",
      "sentiment": "neutral",
      "sentiment_score": 0.7891592383384705,
      "tone": "Neutral",
      "scores": {
        "neutral": 0.7891592383384705,
        "negative": 0.18110373616218567,
        "positive": 0.029737034812569618
      }
    },
    {
      "start": 288.0,
      "end": 293.0,
      "text": "in that utility company will still be the responsible for the related portion of your bill,",
      "sentiment": "neutral",
      "sentiment_score": 0.8478482365608215,
      "tone": "Neutral",
      "scores": {
        "neutral": 0.8478482365608215,
        "negative": 0.10616379231214523,
        "positive": 0.04598803445696831
      }
    },
    {
      "start": 293.0,
      "end": 297.0,
      "text": "reach the middle, build your in-hand low, any service calls and emergency.",
      "sentiment": "neutral",
      "sentiment_score": 0.7277195453643799,
      "tone": "Neutral",
      "scores": {
        "neutral": 0.7277195453643799,
        "positive": 0.22499752044677734,
        "negative": 0.0472828671336174
      }
    },
    {
      "start": 297.0,
      "end": 301.0,
      "text": "They will assume that you are going to receive a well-compact case in the next three to five business",
      "sentiment": "neutral",
      "sentiment_score": 0.7919920682907104,
      "tone": "Neutral",
      "scores": {
        "neutral": 0.7919920682907104,
        "positive": 0.1566057950258255,
        "negative": 0.051402099430561066
      }
    },
    {
      "start": 301.0,
      "end": 305.0,
      "text": "days, and nationally agreed with a sensation of a confirmation leader.",
      "sentiment": "neutral",
      "sentiment_score": 0.826785683631897,
      "tone": "Neutral",
      "scores": {
        "neutral": 0.826785683631897,
        "positive": 0.1465676873922348,
        "negative": 0.026646634563803673
      }
    },
    {
      "start": 305.0,
      "end": 308.0,
      "text": "Once you receive the welcome package, if you have any additional question,",
      "sentiment": "neutral",
      "sentiment_score": 0.8040255308151245,
      "tone": "Neutral",
      "scores": {
        "neutral": 0.8040255308151245,
        "positive": 0.18686577677726746,
        "negative": 0.009108725935220718
      }
    },
    {
      "start": 308.0,
      "end": 311.0,
      "text": "you can call call-comers, if you have a piece of papers that I can give you,",
      "sentiment": "neutral",
      "sentiment_score": 0.8915306329727173,
      "tone": "Neutral",
      "scores": {
        "neutral": 0.8915306329727173,
        "positive": 0.09429915249347687,
        "negative": 0.014170141890645027
      }
    },
    {
      "start": 311.0,
      "end": 319.0,
      "text": "or call-comers service numbers, is 888-355-6205.",
      "sentiment": "neutral",
      "sentiment_score": 0.9029602408409119,
      "tone": "Neutral",
      "scores": {
        "neutral": 0.9029602408409119,
        "positive": 0.0628046914935112,
        "negative": 0.03423503413796425
      }
    },
    {
      "start": 319.0,
      "end": 323.0,
      "text": "Now, during the verification process, they are not allowed to answer any question,",
      "sentiment": "negative",
      "sentiment_score": 0.7024820446968079,
      "tone": "Neutral",
      "scores": {
        "negative": 0.7024820446968079,
        "neutral": 0.2889087498188019,
        "positive": 0.00860918965190649
      }
    },
    {
      "start": 323.0,
      "end": 325.0,
      "text": "therefore do you have any additional question?",
      "sentiment": "neutral",
      "sentiment_score": 0.92603600025177,
      "tone": "Neutral",
      "scores": {
        "neutral": 0.92603600025177,
        "negative": 0.04055074602365494,
        "positive": 0.03341323509812355
      }
    },
    {
      "start": 325.0,
      "end": 328.0,
      "text": "No, no, no.",
      "sentiment": "negative",
      "sentiment_score": 0.48954635858535767,
      "tone": "Neutral",
      "scores": {
        "negative": 0.48954635858535767,
        "neutral": 0.43662968277931213,
        "positive": 0.07382393628358841
      }
    },
    {
      "start": 328.0,
      "end": 329.0,
      "text": "Okay, great.",
      "sentiment": "positive",
      "sentiment_score": 0.9291729927062988,
      "tone": "Neutral",
      "scores": {
        "positive": 0.9291729927062988,
        "neutral": 0.06066695973277092,
        "negative": 0.01016008947044611
      }
    },
    {
      "start": 329.0,
      "end": 333.0,
      "text": "During the verification, if you have any question or you don't give a clear gesture,",
      "sentiment": "neutral",
      "sentiment_score": 0.7194424867630005,
      "tone": "Neutral",
      "scores": {
        "neutral": 0.7194424867630005,
        "negative": 0.2527411878108978,
        "positive": 0.027816353365778923
      }
    },
    {
      "start": 333.0,
      "end": 336.0,
      "text": "now the verification will be to be reserved.",
      "sentiment": "neutral",
      "sentiment_score": 0.9238328337669373,
      "tone": "Neutral",
      "scores": {
        "neutral": 0.9238328337669373,
        "positive": 0.049958646297454834,
        "negative": 0.02620844356715679
      }
    },
    {
      "start": 336.0,
      "end": 337.0,
      "text": "Okay, perfect.",
      "sentiment": "positive",
      "sentiment_score": 0.9282195568084717,
      "tone": "Neutral",
      "scores": {
        "positive": 0.9282195568084717,
        "neutral": 0.06015513837337494,
        "negative": 0.011625300161540508
      }
    },
    {
      "start": 337.0,
      "end": 338.0,
      "text": "Let me leave the line.",
      "sentiment": "neutral",
      "sentiment_score": 0.7327544689178467,
      "tone": "Neutral",
      "scores": {
        "neutral": 0.7327544689178467,
        "negative": 0.17633582651615143,
        "positive": 0.09090972691774368
      }
    },
    {
      "start": 338.0,
      "end": 340.0,
      "text": "The first two questions are for me.",
      "sentiment": "neutral",
      "sentiment_score": 0.8013396859169006,
      "tone": "Neutral",
      "scores": {
        "neutral": 0.8013396859169006,
        "positive": 0.1672849953174591,
        "negative": 0.031375300139188766
      }
    },
    {
      "start": 340.0,
      "end": 341.0,
      "text": "Hope for one moment.",
      "sentiment": "positive",
      "sentiment_score": 0.5532166957855225,
      "tone": "Neutral",
      "scores": {
        "positive": 0.5532166957855225,
        "neutral": 0.38495001196861267,
        "negative": 0.06183331087231636
      }
    },
    {
      "start": 341.0,
      "end": 344.0,
      "text": "If you didn't say it with me on the line, do not hint.",
      "sentiment": "neutral",
      "sentiment_score": 0.5738507509231567,
      "tone": "Neutral",
      "scores": {
        "neutral": 0.5738507509231567,
        "negative": 0.39505451917648315,
        "positive": 0.031094731763005257
      }
    },
    {
      "start": 344.0,
      "end": 346.0,
      "text": "Okay?",
      "sentiment": "neutral",
      "sentiment_score": 0.759236752986908,
      "tone": "Neutral",
      "scores": {
        "neutral": 0.759236752986908,
        "positive": 0.1796017587184906,
        "negative": 0.06116145849227905
      }
    },
    {
      "start": 346.0,
      "end": 347.0,
      "text": "Okay, perfect.",
      "sentiment": "positive",
      "sentiment_score": 0.9282195568084717,
      "tone": "Neutral",
      "scores": {
        "positive": 0.9282195568084717,
        "neutral": 0.06015513837337494,
        "negative": 0.011625300161540508
      }
    },
    {
      "start": 363.0,
      "end": 364.0,
      "text": "Thank you.",
      "sentiment": "positive",
      "sentiment_score": 0.8344851136207581,
      "tone": "Neutral",
      "scores": {
        "positive": 0.8344851136207581,
        "neutral": 0.14667820930480957,
        "negative": 0.018836667761206627
      }
    },
    {
      "start": 393.0,
      "end": 419.0,
      "text": "Thank you.",
      "sentiment": "positive",
      "sentiment_score": 0.8344851136207581,
      "tone": "Neutral",
      "scores": {
        "positive": 0.8344851136207581,
        "neutral": 0.14667820930480957,
        "negative": 0.018836667761206627
      }
    },
    {
      "start": 419.0,
      "end": 429.0,
      "text": "Thank you.",
      "sentiment": "positive",
      "sentiment_score": 0.8344851136207581,
      "tone": "Neutral",
      "scores": {
        "positive": 0.8344851136207581,
        "neutral": 0.14667820930480957,
        "negative": 0.018836667761206627
      }
    },
    {
      "start": 429.0,
      "end": 436.0,
      "text": "Hello, this is Sam with a TPV-36BM, and in the band-end third party,",
      "sentiment": "neutral",
      "sentiment_score": 0.881584107875824,
      "tone": "Neutral",
      "scores": {
        "neutral": 0.881584107875824,
        "positive": 0.10765090584754944,
        "negative": 0.010764974169433117
      }
    },
    {
      "start": 436.0,
      "end": 437.0,
      "text": "we are fire.",
      "sentiment": "positive",
      "sentiment_score": 0.7680156826972961,
      "tone": "Neutral",
      "scores": {
        "positive": 0.7680156826972961,
        "neutral": 0.22090616822242737,
        "negative": 0.011078198440372944
      }
    },
    {
      "start": 437.0,
      "end": 441.0,
      "text": "Today, I will be confirming and recording your position.",
      "sentiment": "neutral",
      "sentiment_score": 0.9212925434112549,
      "tone": "Neutral",
      "scores": {
        "neutral": 0.9212925434112549,
        "positive": 0.07210845500230789,
        "negative": 0.006599006243050098
      }
    },
    {
      "start": 441.0,
      "end": 446.0,
      "text": "To voluntarily select the INSKY energy, as your electricity supplier,",
      "sentiment": "neutral",
      "sentiment_score": 0.9184471964836121,
      "tone": "Neutral",
      "scores": {
        "neutral": 0.9184471964836121,
        "positive": 0.05547625571489334,
        "negative": 0.026076557114720345
      }
    },
    {
      "start": 446.0,
      "end": 451.0,
      "text": "each question must be answered with a clear reaction or response,",
      "sentiment": "neutral",
      "sentiment_score": 0.8184473514556885,
      "tone": "Neutral",
      "scores": {
        "neutral": 0.8184473514556885,
        "positive": 0.13897408545017242,
        "negative": 0.0425785668194294
      }
    },
    {
      "start": 451.0,
      "end": 453.0,
      "text": "and last otherwise requested.",
      "sentiment": "neutral",
      "sentiment_score": 0.8401423692703247,
      "tone": "Neutral",
      "scores": {
        "neutral": 0.8401423692703247,
        "positive": 0.12818801403045654,
        "negative": 0.03166961669921875
      }
    },
    {
      "start": 453.0,
      "end": 463.0,
      "text": "The understanding purpose of this call in fact is being recorded.",
      "sentiment": "neutral",
      "sentiment_score": 0.8900464177131653,
      "tone": "Neutral",
      "scores": {
        "neutral": 0.8900464177131653,
        "positive": 0.06688087433576584,
        "negative": 0.04307278245687485
      }
    },
    {
      "start": 463.0,
      "end": 465.0,
      "text": "I'm sorry, can you hear your voice?",
      "sentiment": "negative",
      "sentiment_score": 0.7500553727149963,
      "tone": "Apologetic",
      "scores": {
        "negative": 0.7500553727149963,
        "neutral": 0.23829732835292816,
        "positive": 0.011647269129753113
      }
    },
    {
      "start": 465.0,
      "end": 469.0,
      "text": "Can you please repeat your response?",
      "sentiment": "neutral",
      "sentiment_score": 0.9103226661682129,
      "tone": "Professional",
      "scores": {
        "neutral": 0.9103226661682129,
        "positive": 0.058382969349622726,
        "negative": 0.031294312328100204
      }
    },
    {
      "start": 469.0,
      "end": 471.0,
      "text": "Do you ask me a question?",
      "sentiment": "neutral",
      "sentiment_score": 0.9251843094825745,
      "tone": "Neutral",
      "scores": {
        "neutral": 0.9251843094825745,
        "negative": 0.039975523948669434,
        "positive": 0.034840233623981476
      }
    },
    {
      "start": 471.0,
      "end": 472.0,
      "text": "I'll answer your question.",
      "sentiment": "neutral",
      "sentiment_score": 0.8016917109489441,
      "tone": "Neutral",
      "scores": {
        "neutral": 0.8016917109489441,
        "positive": 0.17819903790950775,
        "negative": 0.020109301432967186
      }
    },
    {
      "start": 472.0,
      "end": 476.0,
      "text": "Yes, go now.",
      "sentiment": "neutral",
      "sentiment_score": 0.8129364252090454,
      "tone": "Neutral",
      "scores": {
        "neutral": 0.8129364252090454,
        "positive": 0.1538839191198349,
        "negative": 0.033179569989442825
      }
    },
    {
      "start": 476.0,
      "end": 478.0,
      "text": "Let me repeat.",
      "sentiment": "neutral",
      "sentiment_score": 0.7239561676979065,
      "tone": "Neutral",
      "scores": {
        "neutral": 0.7239561676979065,
        "positive": 0.1814415007829666,
        "negative": 0.0946023017168045
      }
    },
    {
      "start": 478.0,
      "end": 483.0,
      "text": "The understand, the purpose of this call in fact is being recorded.",
      "sentiment": "neutral",
      "sentiment_score": 0.8925234079360962,
      "tone": "Neutral",
      "scores": {
        "neutral": 0.8925234079360962,
        "positive": 0.07238690555095673,
        "negative": 0.03508960083127022
      }
    },
    {
      "start": 483.0,
      "end": 488.0,
      "text": "Yes.",
      "sentiment": "neutral",
      "sentiment_score": 0.5811466574668884,
      "tone": "Neutral",
      "scores": {
        "neutral": 0.5811466574668884,
        "positive": 0.3446405827999115,
        "negative": 0.07421278953552246
      }
    },
    {
      "start": 488.0,
      "end": 495.0,
      "text": "Please confirm today's date is April 9th, 2025,",
      "sentiment": "neutral",
      "sentiment_score": 0.891055166721344,
      "tone": "Professional",
      "scores": {
        "neutral": 0.891055166721344,
        "positive": 0.10399235785007477,
        "negative": 0.004952513612806797
      }
    },
    {
      "start": 495.0,
      "end": 506.0,
      "text": "and the time is 11.45 AM, Eastern Standard Time.",
      "sentiment": "neutral",
      "sentiment_score": 0.950072705745697,
      "tone": "Neutral",
      "scores": {
        "neutral": 0.950072705745697,
        "positive": 0.04067976772785187,
        "negative": 0.009247547015547752
      }
    },
    {
      "start": 506.0,
      "end": 513.0,
      "text": "Please estate the customer name as it appears on the National Grid Bill.",
      "sentiment": "neutral",
      "sentiment_score": 0.9063790440559387,
      "tone": "Professional",
      "scores": {
        "neutral": 0.9063790440559387,
        "positive": 0.05896180123090744,
        "negative": 0.034659113734960556
      }
    },
    {
      "start": 513.0,
      "end": 516.0,
      "text": "Janini Kurea.",
      "sentiment": "neutral",
      "sentiment_score": 0.862196683883667,
      "tone": "Neutral",
      "scores": {
        "neutral": 0.862196683883667,
        "positive": 0.07890094816684723,
        "negative": 0.05890246853232384
      }
    },
    {
      "start": 516.0,
      "end": 521.0,
      "text": "Please estate your first and last name.",
      "sentiment": "neutral",
      "sentiment_score": 0.8315891623497009,
      "tone": "Professional",
      "scores": {
        "neutral": 0.8315891623497009,
        "positive": 0.10592472553253174,
        "negative": 0.06248611584305763
      }
    },
    {
      "start": 521.0,
      "end": 525.0,
      "text": "Janini, last name Kurea.",
      "sentiment": "neutral",
      "sentiment_score": 0.9120318293571472,
      "tone": "Neutral",
      "scores": {
        "neutral": 0.9120318293571472,
        "positive": 0.06271476298570633,
        "negative": 0.025253402069211006
      }
    },
    {
      "start": 525.0,
      "end": 530.0,
      "text": "Please estate your phone number.",
      "sentiment": "neutral",
      "sentiment_score": 0.7798827886581421,
      "tone": "Professional",
      "scores": {
        "neutral": 0.7798827886581421,
        "positive": 0.12202927470207214,
        "negative": 0.09808801859617233
      }
    },
    {
      "start": 530.0,
      "end": 537.0,
      "text": "5-0-8-345-6904.",
      "sentiment": "neutral",
      "sentiment_score": 0.8426598310470581,
      "tone": "Neutral",
      "scores": {
        "neutral": 0.8426598310470581,
        "positive": 0.09496428072452545,
        "negative": 0.06237595155835152
      }
    },
    {
      "start": 537.0,
      "end": 538.0,
      "text": "Thank you.",
      "sentiment": "positive",
      "sentiment_score": 0.8344851136207581,
      "tone": "Neutral",
      "scores": {
        "positive": 0.8344851136207581,
        "neutral": 0.14667820930480957,
        "negative": 0.018836667761206627
      }
    },
    {
      "start": 538.0,
      "end": 546.0,
      "text": "Are you the utility bill account holder for person authorized to switch energy suppliers?",
      "sentiment": "neutral",
      "sentiment_score": 0.9245581030845642,
      "tone": "Neutral",
      "scores": {
        "neutral": 0.9245581030845642,
        "negative": 0.03799797594547272,
        "positive": 0.03744399547576904
      }
    },
    {
      "start": 546.0,
      "end": 548.0,
      "text": "Yes.",
      "sentiment": "neutral",
      "sentiment_score": 0.5811466574668884,
      "tone": "Neutral",
      "scores": {
        "neutral": 0.5811466574668884,
        "positive": 0.3446405827999115,
        "negative": 0.07421278953552246
      }
    },
    {
      "start": 548.0,
      "end": 556.0,
      "text": "I have your month and the birth as April 15th, is that your act?",
      "sentiment": "neutral",
      "sentiment_score": 0.9370653629302979,
      "tone": "Neutral",
      "scores": {
        "neutral": 0.9370653629302979,
        "positive": 0.045300282537937164,
        "negative": 0.017634376883506775
      }
    },
    {
      "start": 556.0,
      "end": 559.0,
      "text": "Yes.",
      "sentiment": "neutral",
      "sentiment_score": 0.5811466574668884,
      "tone": "Neutral",
      "scores": {
        "neutral": 0.5811466574668884,
        "positive": 0.3446405827999115,
        "negative": 0.07421278953552246
      }
    },
    {
      "start": 559.0,
      "end": 568.0,
      "text": "Is a 305 Pine Grove Drive, Brockton, MA-02300 on your correct service address?",
      "sentiment": "neutral",
      "sentiment_score": 0.9178875088691711,
      "tone": "Neutral",
      "scores": {
        "neutral": 0.9178875088691711,
        "negative": 0.053592175245285034,
        "positive": 0.028520280495285988
      }
    },
    {
      "start": 568.0,
      "end": 571.0,
      "text": "Yes.",
      "sentiment": "neutral",
      "sentiment_score": 0.5811466574668884,
      "tone": "Neutral",
      "scores": {
        "neutral": 0.5811466574668884,
        "positive": 0.3446405827999115,
        "negative": 0.07421278953552246
      }
    },
    {
      "start": 571.0,
      "end": 578.0,
      "text": "I show your billing address to be the same as your service address.",
      "sentiment": "neutral",
      "sentiment_score": 0.8722519874572754,
      "tone": "Neutral",
      "scores": {
        "neutral": 0.8722519874572754,
        "negative": 0.07635427266359329,
        "positive": 0.05139370262622833
      }
    },
    {
      "start": 578.0,
      "end": 579.0,
      "text": "Is this your act?",
      "sentiment": "neutral",
      "sentiment_score": 0.8785570859909058,
      "tone": "Neutral",
      "scores": {
        "neutral": 0.8785570859909058,
        "negative": 0.09220021218061447,
        "positive": 0.02924267388880253
      }
    },
    {
      "start": 579.0,
      "end": 582.0,
      "text": "That's correct, yes.",
      "sentiment": "neutral",
      "sentiment_score": 0.5335050821304321,
      "tone": "Neutral",
      "scores": {
        "neutral": 0.5335050821304321,
        "positive": 0.45638540387153625,
        "negative": 0.010109505616128445
      }
    },
    {
      "start": 582.0,
      "end": 592.0,
      "text": "I show the account number on your electric bill as 756-960-602-1 is that your act?",
      "sentiment": "neutral",
      "sentiment_score": 0.7415422797203064,
      "tone": "Neutral",
      "scores": {
        "neutral": 0.7415422797203064,
        "negative": 0.236276775598526,
        "positive": 0.02218088135123253
      }
    },
    {
      "start": 592.0,
      "end": 595.0,
      "text": "Yes.",
      "sentiment": "neutral",
      "sentiment_score": 0.5811466574668884,
      "tone": "Neutral",
      "scores": {
        "neutral": 0.5811466574668884,
        "positive": 0.3446405827999115,
        "negative": 0.07421278953552246
      }
    },
    {
      "start": 595.0,
      "end": 610.0,
      "text": "The understand that you are enrolling in a fixed rate electricity plan, which is a 100% renewable product at a price of 20.99 cents per kilowatt hour for an initial term of 12 months?",
      "sentiment": "neutral",
      "sentiment_score": 0.8859459757804871,
      "tone": "Neutral",
      "scores": {
        "neutral": 0.8859459757804871,
        "positive": 0.09204110503196716,
        "negative": 0.022012941539287567
      }
    },
    {
      "start": 610.0,
      "end": 616.0,
      "text": "Yes.",
      "sentiment": "neutral",
      "sentiment_score": 0.5811466574668884,
      "tone": "Neutral",
      "scores": {
        "neutral": 0.5811466574668884,
        "positive": 0.3446405827999115,
        "negative": 0.07421278953552246
      }
    },
    {
      "start": 616.0,
      "end": 628.0,
      "text": "The understand that if you decide to cancel your electricity supply service before the end of the term, you may be charged in early termination fee and the amount of $75.",
      "sentiment": "negative",
      "sentiment_score": 0.5070140957832336,
      "tone": "Neutral",
      "scores": {
        "negative": 0.5070140957832336,
        "neutral": 0.4811922013759613,
        "positive": 0.01179360318928957
      }
    },
    {
      "start": 628.0,
      "end": 632.0,
      "text": "Yes.",
      "sentiment": "neutral",
      "sentiment_score": 0.5811466574668884,
      "tone": "Neutral",
      "scores": {
        "neutral": 0.5811466574668884,
        "positive": 0.3446405827999115,
        "negative": 0.07421278953552246
      }
    },
    {
      "start": 632.0,
      "end": 646.0,
      "text": "Begin sent your allowing King Sky energy to you obtain your historical usage information from your utility company in order to process your enrollment request.",
      "sentiment": "neutral",
      "sentiment_score": 0.8865249752998352,
      "tone": "Neutral",
      "scores": {
        "neutral": 0.8865249752998352,
        "positive": 0.10230684280395508,
        "negative": 0.01116812415421009
      }
    },
    {
      "start": 646.0,
      "end": 649.0,
      "text": "Yes.",
      "sentiment": "neutral",
      "sentiment_score": 0.5811466574668884,
      "tone": "Neutral",
      "scores": {
        "neutral": 0.5811466574668884,
        "positive": 0.3446405827999115,
        "negative": 0.07421278953552246
      }
    },
    {
      "start": 649.0,
      "end": 671.0,
      "text": "The understand that the rubber sun that I've been spoke with earlier rubber suns, King Sky and that, King Sky is not an affiliate of national grid, what is an approved supplier in the energy choice pr...",
      "sentiment": "neutral",
      "sentiment_score": 0.8657730221748352,
      "tone": "Neutral",
      "scores": {
        "neutral": 0.8657730221748352,
        "negative": 0.09895418584346771,
        "positive": 0.03527284041047096
      }
    },
    {
      "start": 671.0,
      "end": 675.0,
      "text": "Yes.",
      "sentiment": "neutral",
      "sentiment_score": 0.5811466574668884,
      "tone": "Neutral",
      "scores": {
        "neutral": 0.5811466574668884,
        "positive": 0.3446405827999115,
        "negative": 0.07421278953552246
      }
    },
    {
      "start": 675.0,
      "end": 686.0,
      "text": "I'm sorry your line is cutting in and out, can you please repeat it?",
      "sentiment": "negative",
      "sentiment_score": 0.8445615172386169,
      "tone": "Apologetic",
      "scores": {
        "negative": 0.8445615172386169,
        "neutral": 0.1470666229724884,
        "positive": 0.008371866308152676
      }
    },
    {
      "start": 686.0,
      "end": 691.0,
      "text": "Can you please say it again, please?",
      "sentiment": "neutral",
      "sentiment_score": 0.696760892868042,
      "tone": "Professional",
      "scores": {
        "neutral": 0.696760892868042,
        "positive": 0.1995754987001419,
        "negative": 0.10366356372833252
      }
    },
    {
      "start": 691.0,
      "end": 694.0,
      "text": "Okay, let me repeat the question.",
      "sentiment": "neutral",
      "sentiment_score": 0.869015097618103,
      "tone": "Neutral",
      "scores": {
        "neutral": 0.869015097618103,
        "positive": 0.07911036908626556,
        "negative": 0.0518745593726635
      }
    },
    {
      "start": 694.0,
      "end": 714.0,
      "text": "Do you understand that the rubber sun that I've been with who you spoke with earlier rubber suns, Queen Sky and that, Queen Sky is not an affiliate of national grid, but is it approved supplier on the...",
      "sentiment": "neutral",
      "sentiment_score": 0.9104831218719482,
      "tone": "Professional",
      "scores": {
        "neutral": 0.9104831218719482,
        "negative": 0.050605881959199905,
        "positive": 0.038911011070013046
      }
    },
    {
      "start": 714.0,
      "end": 717.0,
      "text": "Yes.",
      "sentiment": "neutral",
      "sentiment_score": 0.5811466574668884,
      "tone": "Neutral",
      "scores": {
        "neutral": 0.5811466574668884,
        "positive": 0.3446405827999115,
        "negative": 0.07421278953552246
      }
    },
    {
      "start": 717.0,
      "end": 728.0,
      "text": "Upon successful completion of this verification, Queen Sky energy will send you a welcome package in changing the terms of service for your review.",
      "sentiment": "positive",
      "sentiment_score": 0.7334619760513306,
      "tone": "Neutral",
      "scores": {
        "positive": 0.7334619760513306,
        "neutral": 0.2621024250984192,
        "negative": 0.004435619339346886
      }
    },
    {
      "start": 728.0,
      "end": 736.0,
      "text": "By law, you have until midnight of the ferrid calendar day following receipt of the welcome packet to stop the enrollment process.",
      "sentiment": "neutral",
      "sentiment_score": 0.8419392704963684,
      "tone": "Neutral",
      "scores": {
        "neutral": 0.8419392704963684,
        "negative": 0.13106074929237366,
        "positive": 0.026999978348612785
      }
    },
    {
      "start": 736.0,
      "end": 745.0,
      "text": "And if you select that a plan that includes an early termination fee, you may be required to be a penalty after the rescission for your ends.",
      "sentiment": "neutral",
      "sentiment_score": 0.5641216039657593,
      "tone": "Neutral",
      "scores": {
        "neutral": 0.5641216039657593,
        "negative": 0.42077863216400146,
        "positive": 0.015099778771400452
      }
    },
    {
      "start": 745.0,
      "end": 760.0,
      "text": "To your rescind, your enrollment simply call either your utility company or Queen Sky energy at 888-3556-055. Do you understand?",
      "sentiment": "neutral",
      "sentiment_score": 0.8632371425628662,
      "tone": "Neutral",
      "scores": {
        "neutral": 0.8632371425628662,
        "negative": 0.10858899354934692,
        "positive": 0.028173908591270447
      }
    },
    {
      "start": 760.0,
      "end": 763.0,
      "text": "Yes.",
      "sentiment": "neutral",
      "sentiment_score": 0.5811466574668884,
      "tone": "Neutral",
      "scores": {
        "neutral": 0.5811466574668884,
        "positive": 0.3446405827999115,
        "negative": 0.07421278953552246
      }
    },
    {
      "start": 763.0,
      "end": 776.0,
      "text": "Lastly, your service with Queen Sky energy will begin with the next available meet your rebate or according to your utilities scheduled timeframe for initiating service.",
      "sentiment": "neutral",
      "sentiment_score": 0.8530129790306091,
      "tone": "Neutral",
      "scores": {
        "neutral": 0.8530129790306091,
        "positive": 0.13939279317855835,
        "negative": 0.007594227325171232
      }
    },
    {
      "start": 776.0,
      "end": 791.0,
      "text": "If you decide to cancel your service or if you have any questions about your service, you may call Queen Sky energy at 888-3556-055.",
      "sentiment": "neutral",
      "sentiment_score": 0.6552157402038574,
      "tone": "Neutral",
      "scores": {
        "neutral": 0.6552157402038574,
        "negative": 0.3218381404876709,
        "positive": 0.022946147248148918
      }
    },
    {
      "start": 791.0,
      "end": 794.0,
      "text": "Do you understand?",
      "sentiment": "neutral",
      "sentiment_score": 0.8155053853988647,
      "tone": "Neutral",
      "scores": {
        "neutral": 0.8155053853988647,
        "negative": 0.11373908817768097,
        "positive": 0.07075555622577667
      }
    },
    {
      "start": 794.0,
      "end": 798.0,
      "text": "Yes.",
      "sentiment": "neutral",
      "sentiment_score": 0.5811466574668884,
      "tone": "Neutral",
      "scores": {
        "neutral": 0.5811466574668884,
        "positive": 0.3446405827999115,
        "negative": 0.07421278953552246
      }
    },
    {
      "start": 798.0,
      "end": 816.0,
      "text": "Thank you for your responses and your verification is now complete. Your verification code is T-Lec Thomas 0701260. Thank you for using TBB360 and you have a great day. Goodbye for now.",
      "sentiment": "positive",
      "sentiment_score": 0.9339797496795654,
      "tone": "Neutral",
      "scores": {
        "positive": 0.9339797496795654,
        "neutral": 0.06271042674779892,
        "negative": 0.003309851512312889
      }
    }
  ]
}